enroll/__init__.py
enroll/__main__.py
enroll/accounts.py
enroll/cache.py
enroll/cli.py
enroll/debian.py
enroll/diff.py
enroll/explain.py
enroll/fsutil.py
enroll/harvest.py
enroll/ignore.py
enroll/jinjaturtle.py
enroll/manifest.py
enroll/pathfilter.py
enroll/platform.py
enroll/remote.py
enroll/rpm.py
enroll/schema/__init__.py
enroll/schema/state.schema.json
enroll/sopsutil.py
enroll/systemd.py
enroll/validate.py
enroll/version.py
enroll-0.4.3.dist-info/LICENSE
enroll-0.4.3.dist-info/METADATA
enroll-0.4.3.dist-info/WHEEL
enroll-0.4.3.dist-info/entry_points.txt
enroll-0.4.3.dist-info/RECORD
