Metadata-Version: 2.1
Name: enroll
Version: 0.4.3
Summary: Enroll a server's running state retrospectively into Ansible
Home-page: https://git.mig5.net/mig5/enroll
License: GPL-3.0-or-later
Author: Miguel Jacq
Author-email: mig@mig5.net
Requires-Python: >=3.10,<4.0
Classifier: License :: OSI Approved :: GNU General Public License v3 or later (GPLv3+)
Classifier: Programming Language :: Python :: 3
Classifier: Programming Language :: Python :: 3.10
Classifier: Programming Language :: Python :: 3.11
Classifier: Programming Language :: Python :: 3.12
Requires-Dist: jsonschema (>=4.23.0,<5.0.0)
Requires-Dist: paramiko (>=3.5)
Requires-Dist: pyyaml (>=6,<7)
Project-URL: Repository, https://git.mig5.net/mig5/enroll
